ifc_builder/__init__.py
ifc_builder/helpers.py
ifc_builder/models.py
ifc_builder/template.py
ifc_builder-0.0.1.dist-info/LICENSE
ifc_builder-0.0.1.dist-info/METADATA
ifc_builder-0.0.1.dist-info/WHEEL
ifc_builder-0.0.1.dist-info/top_level.txt
ifc_builder-0.0.1.dist-info/RECORD
